<annotation>
	<folder>Nova pasta</folder>
	<filename>novissimas_62.png</filename>
	<path>C:\Users\wesle\Documents\TensorFlow\workspace\training_demo\Nova pasta\novissimas_62.png</path>
	<source>
		<database>Unknown</database>
	</source>
	<size>
		<width>626</width>
		<height>417</height>
		<depth>3</depth>
	</size>
	<segmented>0</segmented>
	<object>
		<name>mask_weared_incorrect</name>
		<pose>Unspecified</pose>
		<truncated>0</truncated>
		<difficult>0</difficult>
		<bndbox>
			<xmin>260</xmin>
			<ymin>75</ymin>
			<xmax>353</xmax>
			<ymax>206</ymax>
		</bndbox>
	</object>
</annotation>
